Metadata-Version: 1.1
Name: PRCDNS
Version: 0.0.3
Summary: 准确、CDN友好的DNS软件，使用DNS-Over-HTTP
Home-page: https://github.com/lbp0200/PRCDNS
Author: lbp0200
Author-email: lbp0408@gmail.com
License: unlicense
Keywords: DNS
Platform: UNKNOWN
Classifier: Development Status :: 3 - Alpha
Classifier: Intended Audience :: Developers
Classifier: Topic :: Software Development :: Build Tools
Classifier: License :: OSI Approved :: Python Software Foundation License
Classifier: Programming Language :: Python :: 3.5
Classifier: Programming Language :: Python :: 3.6
